fdfat/__init__.py
fdfat/main.py
fdfat/cfg/__init__.py
fdfat/cfg/default.yaml
fdfat/cfg/default_data.yaml
fdfat/cfg/yaml_utils.py
fdfat/cli/__init__.py
fdfat/data/__init__.py
fdfat/data/dataloader.py
fdfat/engine/__init__.py
fdfat/engine/base.py
fdfat/engine/exporter.py
fdfat/engine/predictor.py
fdfat/engine/tester.py
fdfat/engine/trainer.py
fdfat/engine/validator.py
fdfat/engine/loop/__init__.py
fdfat/engine/loop/tester.py
fdfat/engine/loop/trainer.py
fdfat/engine/loop/validator.py
fdfat/metric/__init__.py
fdfat/metric/metric.py
fdfat/nn/__init__.py
fdfat/nn/conv.py
fdfat/nn/model.py
fdfat/nn/module.py
fdfat/nn/module2.py
fdfat/nn/module3.py
fdfat/nn/module4.py
fdfat/nn/module5.py
fdfat/nn/modulecsp.py
fdfat/nn/onnx.py
fdfat/tracking/__init__.py
fdfat/tracking/face.py
fdfat/tracking/facial_sort.py
fdfat/tracking/karman_filter.py
fdfat/tracking/sort.py
fdfat/tracking/utils/__init__.py
fdfat/tracking/utils/logger.py
fdfat/tracking/utils/protocol.py
fdfat/tracking/utils/worker.py
fdfat/tracking/utils/zmq_utils.py
fdfat/utils/__init__.py
fdfat/utils/box_utils.py
fdfat/utils/logger.py
fdfat/utils/model_utils.py
fdfat/utils/pose_estimation.py
fdfat/utils/profiler.py
fdfat/utils/utils.py
fdfat-0.2.6.1.dist-info/METADATA
fdfat-0.2.6.1.dist-info/WHEEL
fdfat-0.2.6.1.dist-info/entry_points.txt
fdfat-0.2.6.1.dist-info/top_level.txt
fdfat-0.2.6.1.dist-info/RECORD
