Metadata-Version: 2.1
Name: fdfat
Version: 0.2.6.1
Summary: Fast 6DoF Face Alignment and Tracking
Home-page: https://github.com/RyanDam/Fast-6DoF-Face-Alignment-and-Tracking
Author: RyanDam
License: GPL-3.0
Keywords: machine-learning,deep-learning,vision,ML,DL,AI
Platform: UNKNOWN
Classifier: Development Status :: 4 - Beta
Classifier: Intended Audience :: Developers
Classifier: Intended Audience :: Education
Classifier: Intended Audience :: Science/Research
Classifier: License :: OSI Approved :: GNU Affero General Public License v3 or later (AGPLv3+)
Classifier: Programming Language :: Python :: 3
Classifier: Programming Language :: Python :: 3.7
Classifier: Programming Language :: Python :: 3.8
Classifier: Programming Language :: Python :: 3.9
Classifier: Programming Language :: Python :: 3.10
Classifier: Programming Language :: Python :: 3.11
Classifier: Topic :: Software Development
Classifier: Topic :: Scientific/Engineering
Classifier: Topic :: Scientific/Engineering :: Artificial Intelligence
Classifier: Topic :: Scientific/Engineering :: Image Recognition
Classifier: Operating System :: POSIX :: Linux
Classifier: Operating System :: MacOS
Classifier: Operating System :: Microsoft :: Windows
Requires-Python: >=3.7
Requires-Dist: matplotlib (>=3.2.2)
Requires-Dist: opencv-python (>=4.6.0)
Requires-Dist: Pillow (>=7.1.2)
Requires-Dist: PyYAML (>=5.3.1)
Requires-Dist: requests (>=2.23.0)
Requires-Dist: scipy (>=1.4.1)
Requires-Dist: torch (>=1.7.0)
Requires-Dist: torchvision (>=0.8.1)
Requires-Dist: tqdm (>=4.64.0)
Requires-Dist: filterpy (>=1.4.5)
Requires-Dist: pandas (>=1.1.4)
Requires-Dist: seaborn (>=0.11.0)
Requires-Dist: psutil
